breathing_cat/__init__.py
breathing_cat/__main__.py
breathing_cat/build.py
breathing_cat/config.py
breathing_cat/find_version.py
breathing_cat/resources/doxygen/Doxyfile.in
breathing_cat/resources/sphinx/cmake_doc.rst.in
breathing_cat/resources/sphinx/conf.py.in
breathing_cat/resources/sphinx/custom.css.in
breathing_cat/resources/sphinx/doxygen_index.rst.in
breathing_cat/resources/sphinx/doxygen_index_one_page.rst.in
breathing_cat/resources/sphinx/general_documentation.rst.in
breathing_cat/resources/sphinx/index.rst.in
breathing_cat-1.4.0.dist-info/LICENSE
breathing_cat-1.4.0.dist-info/METADATA
breathing_cat-1.4.0.dist-info/WHEEL
breathing_cat-1.4.0.dist-info/entry_points.txt
breathing_cat-1.4.0.dist-info/top_level.txt
breathing_cat-1.4.0.dist-info/RECORD
