Metadata-Version: 2.1
Name: breathing_cat
Version: 1.4.0
Summary: Tool to build documentation for C++/Python-Packages used at MPI-IS
Author: Maximilien Naveau, Felix Widmaier
Maintainer-email: Felix Widmaier <felix.widmaier@tuebingen.mpg.de>
Project-URL: Source Code, https://github.com/machines-in-motion/breathing-cat
Project-URL: Bug Tracker, https://github.com/machines-in-motion/breathing-cat/issues
Keywords: documentation,sphinx,doxygen
Classifier: Development Status :: 5 - Production/Stable
Classifier: License :: OSI Approved :: BSD License
Classifier: Programming Language :: Python :: 3.8
Classifier: Programming Language :: Python :: 3.9
Classifier: Programming Language :: Python :: 3.10
Classifier: Programming Language :: Python :: 3.11
Classifier: Programming Language :: Python :: 3.12
Classifier: Topic :: Documentation
Classifier: Topic :: Documentation :: Sphinx
Requires-Python: >=3.8
License-File: LICENSE
Requires-Dist: breathe
Requires-Dist: myst-parser
Requires-Dist: sphinx
Requires-Dist: sphinx-rtd-theme
Requires-Dist: sphinxcontrib-moderncmakedomain
Requires-Dist: variconf[toml]
Provides-Extra: test
Requires-Dist: pytest ; extra == 'test'
